{
    "timestamp":  "2026-03-14T06:43:02+08:00",
    "task_id":  "PHASE2-EXEC",
    "stage":  "Phase10",
    "event":  "session_compacted",
    "summary":  "compact after checkpoint: Runtime stack --with-java-app + decode-runtime strict acceptance verified PASS on RK3588.",
    "root":  "D:\\yihecode-server-master\\yihecode-server-master",
    "pwd":  "D:\\yihecode-server-master\\yihecode-server-master",
    "machine":  "ZQL-CH",
    "user":  "陈豪",
    "is_git_repo":  true,
    "git_branch":  "main",
    "git_status":  [
                       " M process/PROCESS-LOG.md",
                       " M process/latest-status.json",
                       " M scripts/rk3588/lanes/phase2-acceptance.json",
                       " M scripts/rk3588/runtime_api_ctl.py",
                       " M scripts/rk3588/runtime_stack_ctl.py",
                       " M scripts/testing/test_runtime_api_ctl.py",
                       " M scripts/testing/test_runtime_stack_ctl.py",
                       " M state/compact/compact-latest.md",
                       " M state/progress/phase2-status.json",
                       "?? runtime/",
                       "?? state/checkpoints/20260314/checkpoint-20260314-064249-PHASE2-EXEC.json",
                       "?? state/checkpoints/20260314/checkpoint-20260314-064302-PHASE2-EXEC.json"
                   ]
}