{
    "timestamp":  "2026-03-14T11:21:56+08:00",
    "task_id":  "PHASE2-EXEC",
    "stage":  "Phase11",
    "event":  "session_compacted",
    "summary":  "compact after final rk3588 closeout convergence",
    "root":  "D:\\yihecode-server-master\\yihecode-server-master",
    "pwd":  "D:\\yihecode-server-master\\yihecode-server-master",
    "machine":  "ZQL-CH",
    "user":  "陈豪",
    "is_git_repo":  true,
    "git_branch":  "main",
    "git_status":  [
                       " M process/PROCESS-LOG.md",
                       " M process/latest-status.json",
                       "?? runtime/",
                       "?? state/checkpoints/20260314/checkpoint-20260314-112155-PHASE2-EXEC.json"
                   ]
}