{
    "timestamp":  "2026-03-13T12:05:35+08:00",
    "task_id":  "PHASE2-EXEC",
    "stage":  "Phase10",
    "event":  "session_compacted",
    "summary":  "compact after checkpoint: GitHub sync complete at c87c2a7: runtime_stack_smoke output now includes acceptance_gates with thresholds and actual telemetry/capacity metrics for auditable edge gating; RK3588 python regression passed (12/12).",
    "root":  "D:\\yihecode-server-master\\yihecode-server-master",
    "pwd":  "D:\\yihecode-server-master\\yihecode-server-master",
    "machine":  "ZQL-CH",
    "user":  "陈豪",
    "is_git_repo":  true,
    "git_branch":  "main",
    "git_status":  [
                       " M process/PROCESS-LOG.md",
                       " M process/latest-status.json",
                       " M state/compact/compact-latest.md",
                       " M state/progress/phase2-status.json",
                       "?? state/checkpoints/20260313/checkpoint-20260313-120520-PHASE2-EXEC.json",
                       "?? state/checkpoints/20260313/checkpoint-20260313-120535-PHASE2-EXEC.json"
                   ]
}